{"is_source_file": false, "format": "", "description": "", "external_files": [], "external_methods": [], "published": [], "classes": [], "methods": [], "calls": [], "search-terms": ["CI_SNIPPET_PATH_FIX.md", "Sass", "npm install", "export-path-node-bin.sh"], "state": 2, "file_id": 60, "knowledge_revision": 169, "git_revision": "", "hash": "7856bcc899e0d56edee1eb311c8098b6", "format-version": 4, "code-base-name": "UCC-Portal", "filename": "CI_SNIPPET_PATH_FIX.md", "revision_history": [{"169": ""}]}