{"is_source_file": true, "format": "SCSS (Sass)", "description": "This file contains global style resets and base styles for the project, including box-sizing, margin resets, typography, media defaults, form element styles, text overflow handling, and link styles.", "external_files": [], "external_methods": [], "published": [], "classes": [], "methods": [], "calls": [], "search-terms": ["box-sizing", "reset margin", "html, body height", "line-height", "font smoothing", "media defaults", "form styles", "overflow-wrap", "line-height headings", "border", "outline", "text-decoration"], "state": 2, "file_id": 8, "knowledge_revision": 30, "git_revision": "4bde357c295923415c503539cd339caad8d74ec8", "hash": "16931e448bfd1b0b4eb19d61aebe603d", "format-version": 4, "code-base-name": "UCC-Portal", "filename": "scss/globals/_boilerplate.scss", "revision_history": [{"30": "4bde357c295923415c503539cd339caad8d74ec8"}]}